{
  "456237": {
    "name": "Jose Miracle",
    "major": "Informatika",
    "starting_year": 2022,
    "total_attendance": 19,
    "standing": "B",
    "year": 3,
    "last_attendance_time": "2026-01-06 20:47:05"
  },
  "852741": {
    "name": "Emily  Blunt",
    "major": "Economics",
    "starting_year": 2020,
    "total_attendance": 11,
    "standing": "A",
    "year": 4,
    "last_attendance_time": "2025-09-09 18:52:46"
  },
  "963852": {
    "name": "Elon Musk",
    "major": "Robotics",
    "starting_year": 2020,
    "total_attendance": 13,
    "standing": "A",
    "year": 4,
    "last_attendance_time": "2025-09-09 18:53:19"
  },
  "978575": {
    "name": "Rakha Aribawa",
    "major": "Informatika",
    "starting_year": 2022,
    "total_attendance": 7,
    "standing": "B",
    "year": 3,
    "last_attendance_time": "2025-09-09 18:54:09"
  },
  "978788": {
    "name": "Adam Fawwaz Aydin ",
    "major": "Informatika",
    "starting_year": 2022,
    "total_attendance": 7,
    "standing": "A",
    "year": 3,
    "last_attendance_time": "2025-09-09 18:54:48"
  },
  "979988": {
    "name": "Indra Made Prima Nugraha",
    "major": "Informatika",
    "starting_year": 2022,
    "total_attendance": 10,
    "standing": "B",
    "year": 3,
    "last_attendance_time": "2025-09-09 18:57:39"
  },
  "981141": {
    "name": "Elvincent Fernandez",
    "major": "Informatika",
    "starting_year": 2022,
    "total_attendance": 13,
    "standing": "A",
    "year": 3,
    "last_attendance_time": "2026-01-06 20:47:06"
  },
  "981243": {
    "name": "Samuel Devano Siregar",
    "major": "Informatika",
    "starting_year": 2022,
    "total_attendance": 9,
    "standing": "B",
    "year": 3,
    "last_attendance_time": "2026-01-06 20:44:08"
  },
  "981431": {
    "name": "Miracle Christian Makarawung",
    "major": "Informatika",
    "starting_year": 2022,
    "total_attendance": 15,
    "standing": "A",
    "year": 3,
    "last_attendance_time": "2025-09-09 18:58:09"
  },
  "981521": {
    "name": "Dimas Bagus Setya Putra",
    "major": "Informatika",
    "starting_year": 2022,
    "total_attendance": 14,
    "standing": "A",
    "year": 3,
    "last_attendance_time": "2026-01-06 20:44:12"
  },
  "982047": {
    "name": "Takuya Kimura",
    "major": "Sastra Jepang",
    "starting_year": 2010,
    "total_attendance": 16,
    "standing": "A",
    "year": 3,
    "last_attendance_time": "2026-01-06 20:46:57"
  },
  "985612": {
    "name": "Taishi Nakagawa",
    "major": "Hukum",
    "starting_year": 2015,
    "total_attendance": 9,
    "standing": "B",
    "year": 3,
    "last_attendance_time": "2025-09-09 19:00:39"
  },
  "987934": {
    "name": "Park Seo Jun",
    "major": "Kedokteran",
    "starting_year": 2017,
    "total_attendance": 12,
    "standing": "A",
    "year": 3,
    "last_attendance_time": "2025-09-09 19:02:42"
  },
  "989771": {
    "name": "Park Bo Gum",
    "major": "Ilmu Komunikasi",
    "starting_year": 2019,
    "total_attendance": 9,
    "standing": "A",
    "year": 3,
    "last_attendance_time": "2025-09-09 19:02:48"
  },
  "991205": {
    "name": "Minami Hamabe",
    "major": "Desain Grafis",
    "starting_year": 2020,
    "total_attendance": 15,
    "standing": "A",
    "year": 3,
    "last_attendance_time": "2025-08-28 18:49:19"
  },
  "992488": {
    "name": "Meisa Kuroki",
    "major": "Hubungan Internasional",
    "starting_year": 2016,
    "total_attendance": 16,
    "standing": "B",
    "year": 3,
    "last_attendance_time": "2025-09-09 19:04:00"
  },
  "993133": {
    "name": "Kim Ji Won",
    "major": "Farmasi",
    "starting_year": 2018,
    "total_attendance": 17,
    "standing": "A",
    "year": 3,
    "last_attendance_time": "2025-09-09 19:04:09"
  },
  "994522": {
    "name": "Kenjiro Tsuda",
    "major": "Ilmu Komputer",
    "starting_year": 2014,
    "total_attendance": 18,
    "standing": "A",
    "year": 3,
    "last_attendance_time": "2025-09-09 19:04:38"
  },
  "995601": {
    "name": "Keisuke Koide",
    "major": "Administrasi Bisnis",
    "starting_year": 2018,
    "total_attendance": 10,
    "standing": "B",
    "year": 3,
    "last_attendance_time": "2025-08-28 20:33:49"
  },
  "996874": {
    "name": "Jung Hae In",
    "major": "Biologi",
    "starting_year": 2017,
    "total_attendance": 16,
    "standing": "A",
    "year": 3,
    "last_attendance_time": "2025-09-09 19:06:14"
  },
  "997320": {
    "name": "Jo Bo Ah",
    "major": "Teknik Kimia",
    "starting_year": 2016,
    "total_attendance": 16,
    "standing": "A",
    "year": 3,
    "last_attendance_time": "2025-09-09 19:06:18"
  },
  "998015": {
    "name": "IU Lee Ji Eun",
    "major": "Farmasi",
    "starting_year": 2017,
    "total_attendance": 16,
    "standing": "A",
    "year": 3,
    "last_attendance_time": "2025-09-09 19:06:22"
  },
  "998947": {
    "name": "Gou Ayano",
    "major": "Arsitektur",
    "starting_year": 2013,
    "total_attendance": 12,
    "standing": "A",
    "year": 3,
    "last_attendance_time": "2026-01-06 20:45:40"
  },
  "998955": {
    "name": "Yui Yoshioka",
    "major": "Biologi",
    "starting_year": 2012,
    "total_attendance": 14,
    "standing": "A",
    "year": 3,
    "last_attendance_time": "2025-09-09 19:07:57"
  },
  "998968": {
    "name": "Yui Aragaki",
    "major": "Ilmu Komunikasi",
    "starting_year": 2013,
    "total_attendance": 15,
    "standing": "A",
    "year": 3,
    "last_attendance_time": "2025-09-09 19:08:19"
  },
  "998984": {
    "name": "Takeru Satoh",
    "major": "Ilmu Politik",
    "starting_year": 2011,
    "total_attendance": 13,
    "standing": "B",
    "year": 3,
    "last_attendance_time": "2026-01-06 20:46:40"
  },
  "999131": {
    "name": "Lilas Ikuta",
    "major": "Bioteknologi",
    "starting_year": 2017,
    "total_attendance": 18,
    "standing": "A",
    "year": 3,
    "last_attendance_time": "2025-09-09 19:08:28"
  },
  "999152": {
    "name": "Jun Janame",
    "major": "Teknik Sipil",
    "starting_year": 2010,
    "total_attendance": 16,
    "standing": "A",
    "year": 3,
    "last_attendance_time": "2025-09-09 19:08:31"
  },
  "999234": {
    "name": "Arimura Kasumi",
    "major": "Kedokteran",
    "starting_year": 2018,
    "total_attendance": 15,
    "standing": "A",
    "year": 3,
    "last_attendance_time": "2025-09-09 19:08:34"
  },
  "999312": {
    "name": "So Ji Sub",
    "major": "Kehutanan",
    "starting_year": 2012,
    "total_attendance": 15,
    "standing": "A",
    "year": 3,
    "last_attendance_time": "2025-09-09 19:08:39"
  }
}